[
    {
      "id":1,
      "nombre": "Vino Reserva",
      "tipo": "Tinto",
      "precio": "2000",
      "imagen": "./img/product1.jpg",
      "stock": 1,
      "cantidadEnCarrito": 0
    },
    {
      "id":2,
      "nombre": "Vino Premium",
      "tipo": "Blanco",
      "precio": "1800",
      "imagen": "./img/product2.jpg",
      "stock": 2,
      "cantidadEnCarrito": 0
    },
    {
      "id":3,
      "nombre": "Vino Elegante",
      "tipo": "Rosado",
      "precio": "1500",
      "imagen": "./img/product3.jpg",
      "stock": 3,
      "cantidadEnCarrito": 0
    },
    {
      "id":4,
      "nombre": "Vino Gran Enemigo",
      "tipo": "Tinto",
      "precio": "4000",
      "imagen": "./img/product4.jpg",
      "stock": 4,
      "cantidadEnCarrito": 0
    },
    {
      "id":5,
      "nombre": "Vino Durigutti Cabernet Franc",
      "tipo": "Tinto",
      "precio": "3000",
      "imagen": "./img/product5.jpg",
      "stock": 5,
      "cantidadEnCarrito": 0
    },
    {
      "id":6,
      "nombre": "Vino Durigutti Tempranillo",
      "tipo": "Tinto",
      "precio": "3500",
      "imagen": "./img/product1.jpg",
      "stock": 1,
      "cantidadEnCarrito": 0
    },
    {
      "id":7,
      "nombre": "Vino Chardonnay",
      "tipo": "Blanco",
      "precio": "3000",
      "imagen": "./img/product2.jpg",
      "stock": 2,
      "cantidadEnCarrito": 0
    },
    {
      "id":8,
      "nombre": "Vino Extra Premium",
      "tipo": "Espumante",
      "precio": "8000",
      "imagen": "./img/product3.jpg",
      "stock": 3,
      "cantidadEnCarrito": 0
    },
    {
      "id":9,
      "nombre": "Vino Termidor",
      "tipo": "Tinto",
      "precio": "3000",
      "imagen": "./img/product4.jpg",
      "stock": 4,
      "cantidadEnCarrito": 0
    },
    {
      "id":10,
      "nombre": "Vino Uvita Fiesta",
      "tipo": "Blanco",
      "precio": "3500",
      "imagen": "./img/product5.jpg",
      "stock": 5,
      "cantidadEnCarrito": 0
    },
    {
      "id":11,
      "nombre": "Vino Concha y Toro",
      "tipo": "Tinto",
      "precio": "6000",
      "imagen": "./img/product1.jpg",
      "stock": 1,
      "cantidadEnCarrito": 0
    },
    {
      "id":12,
      "nombre": "Vino Pomery",
      "tipo": "Espumante",
      "precio": "8000",
      "imagen": "./img/product2.jpg",
      "stock": 2,
      "cantidadEnCarrito": 0
    }
]